safepath/__init__.py
safepath/safepath.py
safepath-0.1.0a3.dist-info/METADATA
safepath-0.1.0a3.dist-info/WHEEL
safepath-0.1.0a3.dist-info/licenses/LICENSE
safepath-0.1.0a3.dist-info/RECORD
