Metadata-Version: 2.3
Name: safepath
Version: 0.1.0a3
Summary: A Python library providing null-safe attribute and key access through a simple chaining API
Project-URL: Homepage, https://github.com/yourusername/safepath
Project-URL: Repository, https://github.com/yourusername/safepath.git
Project-URL: Issues, https://github.com/yourusername/safepath/issues
Author-email: Alex Wohletz <awohletz3@gmail.com>
License: MIT
Keywords: chaining,null-safe,optional,utility
Classifier: Development Status :: 4 - Beta
Classifier: Intended Audience :: Developers
Classifier: License :: OSI Approved :: MIT License
Classifier: Programming Language :: Python :: 3
Classifier: Programming Language :: Python :: 3.7
Classifier: Programming Language :: Python :: 3.8
Classifier: Programming Language :: Python :: 3.9
Classifier: Programming Language :: Python :: 3.10
Classifier: Programming Language :: Python :: 3.11
Classifier: Programming Language :: Python :: 3.12
Classifier: Topic :: Software Development :: Libraries :: Python Modules
Requires-Python: >=3.7
